latex_document_generator/__init__.py
latex_document_generator/generator.py
latex_document_generator-0.1.0.dist-info/METADATA
latex_document_generator-0.1.0.dist-info/WHEEL
latex_document_generator-0.1.0.dist-info/RECORD
